pygrabber/PyGrabber.py
pygrabber/dshow_core.py
pygrabber/dshow_graph.py
pygrabber/dshow_ids.py
pygrabber/moniker.py
pygrabber/win_api_extra.py
pygrabber/win_common_types.py
pygrabber/windows_media.py
pygrabber-0.1.dist-info/LICENSE
pygrabber-0.1.dist-info/METADATA
pygrabber-0.1.dist-info/WHEEL
pygrabber-0.1.dist-info/top_level.txt
pygrabber-0.1.dist-info/RECORD
