Metadata-Version: 1.0
Name: pygrabber
Version: 0.1
Summary: Module for grabbing live video images using DirectShow
Home-page: https://github.com/andreaschiavinato/python_grabber
Author: andreaschiavinato
Author-email: UNKNOWN
License: MIT
Platform: UNKNOWN
